MANIFEST.in
README.md
setup.cfg
setup.py
docs/HISTORY.txt
docs/INSTALL.txt
docs/LICENSE.GPL
docs/LICENSE.txt
vbeo/.DS_Store
vbeo/__init__.py
vbeo.seantis.dir.events.egg-info/PKG-INFO
vbeo.seantis.dir.events.egg-info/SOURCES.txt
vbeo.seantis.dir.events.egg-info/dependency_links.txt
vbeo.seantis.dir.events.egg-info/entry_points.txt
vbeo.seantis.dir.events.egg-info/namespace_packages.txt
vbeo.seantis.dir.events.egg-info/not-zip-safe
vbeo.seantis.dir.events.egg-info/requires.txt
vbeo.seantis.dir.events.egg-info/top_level.txt
vbeo/seantis/.DS_Store
vbeo/seantis/__init__.py
vbeo/seantis/dir/.DS_Store
vbeo/seantis/dir/__init__.py
vbeo/seantis/dir/events/.DS_Store
vbeo/seantis/dir/events/__init__.py
vbeo/seantis/dir/events/configure.zcml
vbeo/seantis/dir/events/guidle.py
vbeo/seantis/dir/events/interfaces.py
vbeo/seantis/dir/events/setuphandlers.py
vbeo/seantis/dir/events/sync.sh
vbeo/seantis/dir/events/upgrades.py
vbeo/seantis/dir/events/css/ie10fixes.css
vbeo/seantis/dir/events/css/ie8fixes.css
vbeo/seantis/dir/events/css/ie9fixes.css
vbeo/seantis/dir/events/css/vbeo.directory.css
vbeo/seantis/dir/events/images/singlemarker.png
vbeo/seantis/dir/events/images/markers/marker-A.png
vbeo/seantis/dir/events/images/markers/marker-B.png
vbeo/seantis/dir/events/images/markers/marker-C.png
vbeo/seantis/dir/events/images/markers/marker-D.png
vbeo/seantis/dir/events/images/markers/marker-E.png
vbeo/seantis/dir/events/images/markers/marker-F.png
vbeo/seantis/dir/events/images/markers/marker-G.png
vbeo/seantis/dir/events/images/markers/marker-H.png
vbeo/seantis/dir/events/images/markers/marker-I.png
vbeo/seantis/dir/events/images/markers/marker-J.png
vbeo/seantis/dir/events/images/markers/marker-K.png
vbeo/seantis/dir/events/images/markers/marker-L.png
vbeo/seantis/dir/events/images/markers/marker-M.png
vbeo/seantis/dir/events/images/markers/marker-N.png
vbeo/seantis/dir/events/images/markers/marker-O.png
vbeo/seantis/dir/events/images/markers/marker-P.png
vbeo/seantis/dir/events/images/markers/marker-Q.png
vbeo/seantis/dir/events/images/markers/marker-R.png
vbeo/seantis/dir/events/images/markers/marker-S.png
vbeo/seantis/dir/events/images/markers/marker-T.png
vbeo/seantis/dir/events/images/markers/marker-U.png
vbeo/seantis/dir/events/images/markers/marker-V.png
vbeo/seantis/dir/events/images/markers/marker-W.png
