Metadata-Version: 1.1
Name: vbeo.seantis.dir.events
Version: 1.1.1
Summary: Integration of seantis.dir.events for Volkswirtschaft Berner Oberland
Home-page: https://github.com/seantis/vbeo.seantis.dir.events
Author: Seantis GmbH
Author-email: info@seantis.ch
License: GPL
Platform: UNKNOWN
Classifier: Framework :: Plone
Classifier: Programming Language :: Python
